setup.py
pycombine/__init__.py
pycombine/pycombine.py
pycombine.egg-info/PKG-INFO
pycombine.egg-info/SOURCES.txt
pycombine.egg-info/dependency_links.txt
pycombine.egg-info/entry_points.txt
pycombine.egg-info/top_level.txt